mel/__init__.py
mel/cli.py
my_mel-0.2.0.dist-info/METADATA
my_mel-0.2.0.dist-info/WHEEL
my_mel-0.2.0.dist-info/entry_points.txt
my_mel-0.2.0.dist-info/RECORD
